hone/__init__.py
hone/agent.py
hone/client.py
hone/providers.py
hone/tools.py
hone/types.py
honeagents_hone-0.1.1.dist-info/METADATA
honeagents_hone-0.1.1.dist-info/WHEEL
honeagents_hone-0.1.1.dist-info/RECORD
