Metadata-Version: 2.4
Name: honeagents-hone
Version: 0.1.1
Summary: Hone SDK - AI Experience Engineering Platform for tracking and improving LLM applications
Project-URL: Homepage, https://honeagents.ai
Project-URL: Documentation, https://honeagents.ai/docs
Project-URL: Repository, https://github.com/honeagents/hone-py
Project-URL: Issues, https://github.com/honeagents/hone-py/issues
Author-email: Hone Team <team@honeagents.ai>
License-Expression: MIT
Keywords: ai,anthropic,evaluation,hone,langsmith,llm,observability,openai,tracing
Classifier: Development Status :: 3 - Alpha
Classifier: Intended Audience :: Developers
Classifier: License :: OSI Approved :: MIT License
Classifier: Programming Language :: Python :: 3
Classifier: Programming Language :: Python :: 3.8
Classifier: Programming Language :: Python :: 3.9
Classifier: Programming Language :: Python :: 3.10
Classifier: Programming Language :: Python :: 3.11
Classifier: Programming Language :: Python :: 3.12
Classifier: Programming Language :: Python :: 3.13
Classifier: Topic :: Software Development :: Libraries :: Python Modules
Requires-Python: >=3.8
Requires-Dist: httpx>=0.24.0
Provides-Extra: dev
Requires-Dist: mypy>=1.0.0; extra == 'dev'
Requires-Dist: pytest-asyncio>=0.21.0; extra == 'dev'
Requires-Dist: pytest-mock>=3.10.0; extra == 'dev'
Requires-Dist: pytest>=7.0.0; extra == 'dev'
Requires-Dist: respx>=0.20.0; extra == 'dev'
Requires-Dist: ruff>=0.1.0; extra == 'dev'
